atomap/__init__.py
atomap/analysis_tools.py
atomap/animation_plotting_tools.py
atomap/api.py
atomap/atom_finding_refining.py
atomap/atom_lattice.py
atomap/atom_plane.py
atomap/atom_position.py
atomap/conftest.py
atomap/convert_ase.py
atomap/dummy_data.py
atomap/example_data.py
atomap/fitting_tools.py
atomap/gui_classes.py
atomap/initial_position_finding.py
atomap/io.py
atomap/main.py
atomap/plotting.py
atomap/process_parameters.py
atomap/quantification.py
atomap/stats.py
atomap/sublattice.py
atomap/symmetry_finding.py
atomap/testing_tools.py
atomap/tools.py
atomap/example_data/example_detector_image.hspy
atomap/example_data/simulated_nanoparticle.hspy
atomap/external/__init__.py
atomap/external/gaussian2d.py
atomap/tests/__init__.py
atomap/tests/test_adf_abf_sto.py
atomap/tests/test_analysis_tools.py
atomap/tests/test_animation_plotting_tools.py
atomap/tests/test_ase_import.py
atomap/tests/test_atom_finding_refining.py
atomap/tests/test_atom_lattice.py
atomap/tests/test_atom_plane.py
atomap/tests/test_atom_position.py
atomap/tests/test_dummy_data.py
atomap/tests/test_example_data.py
atomap/tests/test_fitting_accuracy.py
atomap/tests/test_fitting_tools.py
atomap/tests/test_gui_function_qt.py
atomap/tests/test_initial_position_finding.py
atomap/tests/test_io.py
atomap/tests/test_main.py
atomap/tests/test_peak_separation.py
atomap/tests/test_plotting.py
atomap/tests/test_process_parameters.py
atomap/tests/test_quantification.py
atomap/tests/test_stats.py
atomap/tests/test_sublattice.py
atomap/tests/test_symmetry_finding.py
atomap/tests/test_testing_tools.py
atomap/tests/test_tools.py
atomap/tests/datasets/__init__.py
atomap/tests/datasets/dataset_filenames.py
atomap/tests/datasets/test_ABF_cropped.hdf5
atomap/tests/datasets/test_ADF_cropped.hdf5
atomap/tests/datasets/test_atom_lattice.hdf5
atomap-0.4.2.dist-info/LICENSE
atomap-0.4.2.dist-info/METADATA
atomap-0.4.2.dist-info/WHEEL
atomap-0.4.2.dist-info/top_level.txt
atomap-0.4.2.dist-info/RECORD
