Metadata-Version: 2.1
Name: atomap
Version: 0.4.2
Summary: Library for analysing atomic resolution images
Author-email: Magnus Nord <magnunor@gmail.com>
License:                     GNU GENERAL PUBLIC LICENSE
Project-URL: Homepage, https://atomap.org/
Project-URL: Documentation, https://atomap.org/finding_atom_lattices.html
Project-URL: Repository, https://gitlab.com/atomap/atomap
Project-URL: Issues, https://gitlab.com/atomap/atomap/-/issues
Keywords: STEM,data analysis,microscopy,transmission electron microscopy
Classifier: Development Status :: 3 - Alpha
Classifier: License :: OSI Approved :: GNU General Public License v3 (GPLv3)
Classifier: Intended Audience :: Science/Research
Classifier: Programming Language :: Python :: 3
License-File: LICENSE
Requires-Dist: scipy>=1.4.0
Requires-Dist: numpy>=1.13
Requires-Dist: h5py
Requires-Dist: matplotlib>=3.1.0
Requires-Dist: scikit-learn
Requires-Dist: scikit-image>=0.17.1
Requires-Dist: hyperspy>=2.0.0
Requires-Dist: ase>=3.17.0
Requires-Dist: numba
Requires-Dist: exspy
